README.txt
setup.py
Scene/__init__.py
Scene/base_scene.py
Scene/class_scene.py
Scene/class_scene3d.py
Scene/class_scene_Gl.py
Scene/class_scene_pygame.py
Scene/class_scene_svg.py
Scene/magnet_scene_GL.py
Scene/stream_io.py
Scene_tz.egg-info/PKG-INFO
Scene_tz.egg-info/SOURCES.txt
Scene_tz.egg-info/dependency_links.txt
Scene_tz.egg-info/top_level.txt